{
  "formatVersion": 1,
  "database": {
    "version": 1,
    "identityHash": "3f80c9ac503343cda54d9bcae67c8210",
    "entities": [
      {
        "tableName": "configurations",
        "createSql": "CREATE TABLE IF NOT EXISTS `${TABLE_NAME}` (`id` INTEGER PRIMARY KEY AUTOINCREMENT NOT NULL, `createDate` INTEGER NOT NULL, `modifyDate` INTEGER NOT NULL, `today` TEXT NOT NULL, `remainDuration` INTEGER NOT NULL, `status` INTEGER NOT NULL, `durationOfEachViewing` INTEGER NOT NULL, `maxViewsCount` INTEGER NOT NULL, `remainViewCount` INTEGER NOT NULL, `minViewInterval` INTEGER NOT NULL)",
        "fields": [
          {
            "fieldPath": "id",
            "columnName": "id",
            "affinity": "INTEGER",
            "notNull": true
          },
          {
            "fieldPath": "createDate",
            "columnName": "createDate",
            "affinity": "INTEGER",
            "notNull": true
          },
          {
            "fieldPath": "modifyDate",
            "columnName": "modifyDate",
            "affinity": "INTEGER",
            "notNull": true
          },
          {
            "fieldPath": "today",
            "columnName": "today",
            "affinity": "TEXT",
            "notNull": true
          },
          {
            "fieldPath": "remainDuration",
            "columnName": "remainDuration",
            "affinity": "INTEGER",
            "notNull": true
          },
          {
            "fieldPath": "status",
            "columnName": "status",
            "affinity": "INTEGER",
            "notNull": true
          },
          {
            "fieldPath": "durationOfEachViewing",
            "columnName": "durationOfEachViewing",
            "affinity": "INTEGER",
            "notNull": true
          },
          {
            "fieldPath": "maxViewsCount",
            "columnName": "maxViewsCount",
            "affinity": "INTEGER",
            "notNull": true
          },
          {
            "fieldPath": "remainViewCount",
            "columnName": "remainViewCount",
            "affinity": "INTEGER",
            "notNull": true
          },
          {
            "fieldPath": "minViewInterval",
            "columnName": "minViewInterval",
            "affinity": "INTEGER",
            "notNull": true
          }
        ],
        "primaryKey": {
          "autoGenerate": true,
          "columnNames": [
            "id"
          ]
        },
        "indices": [],
        "foreignKeys": []
      },
      {
        "tableName": "ConfigurationHistories",
        "createSql": "CREATE TABLE IF NOT EXISTS `${TABLE_NAME}` (`id` INTEGER PRIMARY KEY AUTOINCREMENT NOT NULL)",
        "fields": [
          {
            "fieldPath": "id",
            "columnName": "id",
            "affinity": "INTEGER",
            "notNull": true
          }
        ],
        "primaryKey": {
          "autoGenerate": true,
          "columnNames": [
            "id"
          ]
        },
        "indices": [],
        "foreignKeys": []
      }
    ],
    "views": [],
    "setupQueries": [
      "CREATE TABLE IF NOT EXISTS room_master_table (id INTEGER PRIMARY KEY,identity_hash TEXT)",
      "INSERT OR REPLACE INTO room_master_table (id,identity_hash) VALUES(42, '3f80c9ac503343cda54d9bcae67c8210')"
    ]
  }
}